{
  "menus": [
    {
      "name": "Big mac",
      "slug": "big-mac",
      "image": "big-mac.jpg",
      "id": 1,
      "price": 8,
      "composition": [
        {
          "name": "Iguaçu Falls",
          "slug": "iguacu-falls"
        },
        {
          "name": "Pão de Açúcar",
          "slug": "pao-de-acucar"
        },
        {
          "name": "Sao Paulo",
          "slug": "sao-paulo"
        },
        {
          "name": "Salvador",
          "slug": "salvador"
        }
      ]
    },
    {
      "name": "Cheeseburger",
      "slug": "cheeseburger",
      "image": "cheeseburger.jpg",
      "id": 2,
      "price": 5,
      "composition": [
        {
          "name": "Panama City",
          "slug": "panama-city"
        },
        {
          "name": "Panama Canal",
          "slug": "panama-canal"
        },
        {
          "name": "Bocas del Toro",
          "slug": "bocas-del-toro"
        },
        {
          "name": "Santa Catalina",
          "slug": "santa-catalina"
        }
      ]
    },
    {
      "name": "Double cheese",
      "slug": "double-cheese",
      "image": "double-cheese.jpg",
      "id": 3,
      "price": 7,
      "composition": [
        {
          "name": "Na Pali Coast",
          "slug": "na-pali-coast"
        },
        {
          "name": "O'Ahu's North Shore",
          "slug": "ohaus-north-shore"
        },
        {
          "name": "Waikiki Beach",
          "slug": "waikiki-beach"
        },
        {
          "name": "Kilauea Volcano",
          "slug": "kilauea-volcano"
        }
      ]
    },
    {
      "name": "CBO",
      "slug": "cbo",
      "image": "cbo.jpg",
      "id": 4,
      "price": 12,
      "composition": [
        {
          "name": "Tower Isle",
          "slug": "tower-isle"
        },
        {
          "name": "Blue Mountain",
          "slug": "blue-mountain"
        },
        {
          "name": "Montego Bay",
          "slug": "montego-bay"
        },
        {
          "name": "Port Antonio",
          "slug": "port-antonio"
        }
      ]
    }
  ]
}